README.md
setup.py
jconfig/__init__.py
jconfig/base.py
jconfig/jconfig.py
jconfig/memory.py
new_vk/__init__.py
new_vk/audio.py
new_vk/audio_url_decoder.py
new_vk/bot_longpoll.py
new_vk/enums.py
new_vk/exceptions.py
new_vk/execute.py
new_vk/keyboard.py
new_vk/longpoll.py
new_vk/requests_pool.py
new_vk/streaming.py
new_vk/tools.py
new_vk/upload.py
new_vk/utils.py
new_vk/vk_api.py
new_vk.egg-info/PKG-INFO
new_vk.egg-info/SOURCES.txt
new_vk.egg-info/dependency_links.txt
new_vk.egg-info/requires.txt
new_vk.egg-info/top_level.txt