Metadata-Version: 2.1
Name: new-vk
Version: 1.0
Summary: Python модуль для написания скриптов для социальной сети Вконтакте (vk.com) (API wrapper)
Home-page: https://github.com/Warale/new_vk
Author: Warale
Author-email: waralegit@yandex.ru
License: Apache License, Version 2.0, see LICENSE file
Download-URL: https://github.com/Warale/new_vk/archive/master.zip
Platform: UNKNOWN
Classifier: License :: OSI Approved :: Apache Software License
Classifier: Operating System :: OS Independent
Classifier: Programming Language :: Python
Classifier: Programming Language :: Python :: 2
Classifier: Programming Language :: Python :: 2.7
Classifier: Programming Language :: Python :: 3
Classifier: Programming Language :: Python :: 3.4
Classifier: Programming Language :: Python :: 3.5
Classifier: Programming Language :: Python :: 3.6
Classifier: Programming Language :: Python :: 3.7
Classifier: Programming Language :: Python :: Implementation :: PyPy
Classifier: Programming Language :: Python :: Implementation :: CPython
Provides-Extra: vkstreaming
Provides-Extra: vkaudio
